<?xml version="1.0" encoding="UTF-8"?>
<DatosEnergeticosDelEdificio version="1.0">
	<DatosDelCertificador>
		<NombreyApellidos>-</NombreyApellidos>
		<NIF>-</NIF>
		<RazonSocial>-</RazonSocial>
		<NIFEntidad>-</NIFEntidad>
		<Domicilio/>
		<Municipio/>
		<CodigoPostal/>
		<Provincia/>
		<ComunidadAutonoma>Andalucía</ComunidadAutonoma>
		<Email>-</Email>
		<Titulacion>-</Titulacion>
		<Fecha>26/03/2014</Fecha>
	</DatosDelCertificador>
	<IdentificacionEdificio>
		<NombreDelEdificio>Vado_166</NombreDelEdificio>
		<Direccion>c/Feria nº7</Direccion>
		<Municipio>Sevilla</Municipio>
		<CodigoPostal>1648173088</CodigoPostal>
		<Provincia>Sevilla</Provincia>
		<ComunidadAutonoma>Andalucía</ComunidadAutonoma>
		<ZonaClimatica>B4</ZonaClimatica>
		<AnoConstruccion/>
		<ReferenciaCatastral>ninguno</ReferenciaCatastral>
		<TipoDeEdificio>ViviendaUnifamiliar</TipoDeEdificio>
		<NormativaVigente>-</NormativaVigente>
		<Procedimiento>HU CTE-HE y CEE Versión 0.9.887.778, de fecha 26-mar-2014</Procedimiento>
		<AlcanceInformacionXML>VerificacionNuevo</AlcanceInformacionXML>
	</IdentificacionEdificio>
	<DatosGeneralesyGeometria>
		<NumeroDePlantasSobreRasante>0</NumeroDePlantasSobreRasante>
		<NumeroDePlantasBajoRasante>0</NumeroDePlantasBajoRasante>
		<SuperficieHabitable>164.44</SuperficieHabitable>
		<VolumenEspacioHabitable>410.76</VolumenEspacioHabitable>
		<Compacidad>4.29</Compacidad>
		<PorcentajeSuperficieHabitableCalefactada>0</PorcentajeSuperficieHabitableCalefactada>
		<PorcentajeSuperficieHabitableRefrigerada>0</PorcentajeSuperficieHabitableRefrigerada>
		<PorcentajeSuperficieAcristalada>
			<N>32</N>
			<NE>0</NE>
			<E>0</E>
			<SE>0</SE>
			<S>26</S>
			<SO>0</SO>
			<O>0</O>
			<NO>0</NO>
		</PorcentajeSuperficieAcristalada>
		<Imagen>E:\Documentos\Mis Proyectos CTE-HE\Proyectos\ejemploa\</Imagen>
		<Plano>E:\Documentos\Mis Proyectos CTE-HE\Proyectos\ejemploa\</Plano>
		<DensidadFuentesInternas>5.77</DensidadFuentesInternas>
		<VentilacionUsoResidencial>0.00</VentilacionUsoResidencial>
		<VentilacionTotal>0.00</VentilacionTotal>
	</DatosGeneralesyGeometria>
	<DatosEnvolventeTermica>
		<CerramientosOpacos>
			<Elemento>
				<Nombre>Muro Exterior</Nombre>
				<Tipo>CERRAMIENTOS CSS</Tipo>
				<Superficie>95.70</Superficie>
				<Transmitancia>0.48</Transmitancia>
				<ModoDeObtencion>Usuario</ModoDeObtencion>
				<Capas>
					<Capa>
						<Material>1/2 pie LM métrico o catalán 40 mm&lt; G &lt; 50 mm</Material>
						<Espesor>0.1150</Espesor>
						<ConductividadTermica>1.02</ConductividadTermica>
						<Densidad>2170.00</Densidad>
						<FactorResistenciaVapor>0.20</FactorResistenciaVapor>
						<CalorEspecifico>1000.00</CalorEspecifico>
					</Capa>
					<Capa>
						<Material>Mortero de cemento o cal para albañilería y para revoco/enlucido 1000 &lt; d &lt; 1250</Material>
						<Espesor>0.0100</Espesor>
						<ConductividadTermica>0.55</ConductividadTermica>
						<Densidad>1125.00</Densidad>
						<FactorResistenciaVapor>0.20</FactorResistenciaVapor>
						<CalorEspecifico>1000.00</CalorEspecifico>
					</Capa>
					<Capa>
						<Material>EPS Poliestireno Expandido [ 0.037 W/[mK]]</Material>
						<Espesor>0.0600</Espesor>
						<ConductividadTermica>0.04</ConductividadTermica>
						<Densidad>30.00</Densidad>
						<FactorResistenciaVapor>0.20</FactorResistenciaVapor>
						<CalorEspecifico>1000.00</CalorEspecifico>
					</Capa>
					<Capa>
						<Material>Tabicón de LH doble [60 mm &lt; E &lt; 90 mm]</Material>
						<Espesor>0.0600</Espesor>
						<ConductividadTermica>0.47</ConductividadTermica>
						<Densidad>930.00</Densidad>
						<FactorResistenciaVapor>0.20</FactorResistenciaVapor>
						<CalorEspecifico>1000.00</CalorEspecifico>
					</Capa>
					<Capa>
						<Material>Enlucido de yeso 1000 &lt; d &lt; 1300</Material>
						<Espesor>0.0100</Espesor>
						<ConductividadTermica>0.57</ConductividadTermica>
						<Densidad>1150.00</Densidad>
						<FactorResistenciaVapor>0.20</FactorResistenciaVapor>
						<CalorEspecifico>1000.00</CalorEspecifico>
					</Capa>
				</Capas>
			</Elemento>
			<Elemento>
				<Nombre>Tabiques</Nombre>
				<Tipo>CERRAMIENTOS CSS</Tipo>
				<Superficie>90.78</Superficie>
				<Transmitancia>2.54</Transmitancia>
				<ModoDeObtencion>Usuario</ModoDeObtencion>
				<Capas>
					<Capa>
						<Material>Enlucido de yeso 1000 &lt; d &lt; 1300</Material>
						<Espesor>0.0100</Espesor>
						<ConductividadTermica>0.57</ConductividadTermica>
						<Densidad>1150.00</Densidad>
						<FactorResistenciaVapor>0.20</FactorResistenciaVapor>
						<CalorEspecifico>1000.00</CalorEspecifico>
					</Capa>
					<Capa>
						<Material>Tabicón de LH doble [60 mm &lt; E &lt; 90 mm]</Material>
						<Espesor>0.0800</Espesor>
						<ConductividadTermica>0.47</ConductividadTermica>
						<Densidad>930.00</Densidad>
						<FactorResistenciaVapor>0.20</FactorResistenciaVapor>
						<CalorEspecifico>1000.00</CalorEspecifico>
					</Capa>
					<Capa>
						<Material>Enlucido de yeso 1000 &lt; d &lt; 1300</Material>
						<Espesor>0.0200</Espesor>
						<ConductividadTermica>0.57</ConductividadTermica>
						<Densidad>1150.00</Densidad>
						<FactorResistenciaVapor>0.20</FactorResistenciaVapor>
						<CalorEspecifico>1000.00</CalorEspecifico>
					</Capa>
				</Capas>
			</Elemento>
			<Elemento>
				<Nombre>Cubierta</Nombre>
				<Tipo>CERRAMIENTOS CSS</Tipo>
				<Superficie>72.89</Superficie>
				<Transmitancia>0.38</Transmitancia>
				<ModoDeObtencion>Usuario</ModoDeObtencion>
				<Capas>
					<Capa>
						<Material>Azulejo cerámico</Material>
						<Espesor>0.0100</Espesor>
						<ConductividadTermica>1.30</ConductividadTermica>
						<Densidad>2300.00</Densidad>
						<FactorResistenciaVapor>0.20</FactorResistenciaVapor>
						<CalorEspecifico>840.00</CalorEspecifico>
					</Capa>
					<Capa>
						<Material>Mortero de cemento o cal para albañilería y para revoco/enlucido 1000 &lt; d &lt; 1250</Material>
						<Espesor>0.0100</Espesor>
						<ConductividadTermica>0.55</ConductividadTermica>
						<Densidad>1125.00</Densidad>
						<FactorResistenciaVapor>0.20</FactorResistenciaVapor>
						<CalorEspecifico>1000.00</CalorEspecifico>
					</Capa>
					<Capa>
						<Material>Tabicón de LH doble [60 mm &lt; E &lt; 90 mm]</Material>
						<Espesor>0.0600</Espesor>
						<ConductividadTermica>0.47</ConductividadTermica>
						<Densidad>930.00</Densidad>
						<FactorResistenciaVapor>0.20</FactorResistenciaVapor>
						<CalorEspecifico>1000.00</CalorEspecifico>
					</Capa>
					<Capa>
						<Material>EPS Poliestireno Expandido [ 0.037 W/[mK]]</Material>
						<Espesor>0.0800</Espesor>
						<ConductividadTermica>0.04</ConductividadTermica>
						<Densidad>30.00</Densidad>
						<FactorResistenciaVapor>0.20</FactorResistenciaVapor>
						<CalorEspecifico>1000.00</CalorEspecifico>
					</Capa>
					<Capa>
						<Material>Hormigón en masa 2000 &lt; d &lt; 2300</Material>
						<Espesor>0.2100</Espesor>
						<ConductividadTermica>1.65</ConductividadTermica>
						<Densidad>2150.00</Densidad>
						<FactorResistenciaVapor>0.20</FactorResistenciaVapor>
						<CalorEspecifico>1000.00</CalorEspecifico>
					</Capa>
					<Capa>
						<Material>Enlucido de yeso 1000 &lt; d &lt; 1300</Material>
						<Espesor>0.0200</Espesor>
						<ConductividadTermica>0.57</ConductividadTermica>
						<Densidad>1150.00</Densidad>
						<FactorResistenciaVapor>0.20</FactorResistenciaVapor>
						<CalorEspecifico>1000.00</CalorEspecifico>
					</Capa>
				</Capas>
			</Elemento>
			<Elemento>
				<Nombre>Forjado interno</Nombre>
				<Tipo>CERRAMIENTOS CSS</Tipo>
				<Superficie>157.86</Superficie>
				<Transmitancia>0.59</Transmitancia>
				<ModoDeObtencion>Usuario</ModoDeObtencion>
				<Capas>
					<Capa>
						<Material>Azulejo cerámico</Material>
						<Espesor>0.0300</Espesor>
						<ConductividadTermica>1.30</ConductividadTermica>
						<Densidad>2300.00</Densidad>
						<FactorResistenciaVapor>0.20</FactorResistenciaVapor>
						<CalorEspecifico>840.00</CalorEspecifico>
					</Capa>
					<Capa>
						<Material>Mortero de cemento o cal para albañilería y para revoco/enlucido 1000 &lt; d &lt; 1250</Material>
						<Espesor>0.0100</Espesor>
						<ConductividadTermica>0.55</ConductividadTermica>
						<Densidad>1125.00</Densidad>
						<FactorResistenciaVapor>0.20</FactorResistenciaVapor>
						<CalorEspecifico>1000.00</CalorEspecifico>
					</Capa>
					<Capa>
						<Material>EPS Poliestireno Expandido [ 0.037 W/[mK]]</Material>
						<Espesor>0.0500</Espesor>
						<ConductividadTermica>0.04</ConductividadTermica>
						<Densidad>30.00</Densidad>
						<FactorResistenciaVapor>0.20</FactorResistenciaVapor>
						<CalorEspecifico>1000.00</CalorEspecifico>
					</Capa>
					<Capa>
						<Material>Hormigón en masa 2000 &lt; d &lt; 2300</Material>
						<Espesor>0.2100</Espesor>
						<ConductividadTermica>1.65</ConductividadTermica>
						<Densidad>2150.00</Densidad>
						<FactorResistenciaVapor>0.20</FactorResistenciaVapor>
						<CalorEspecifico>1000.00</CalorEspecifico>
					</Capa>
					<Capa>
						<Material>Enlucido de yeso 1000 &lt; d &lt; 1300</Material>
						<Espesor>0.0100</Espesor>
						<ConductividadTermica>0.57</ConductividadTermica>
						<Densidad>1150.00</Densidad>
						<FactorResistenciaVapor>0.20</FactorResistenciaVapor>
						<CalorEspecifico>1000.00</CalorEspecifico>
					</Capa>
				</Capas>
			</Elemento>
			<Elemento>
				<Nombre>Forjado terreno</Nombre>
				<Tipo>CERRAMIENTOS CSS</Tipo>
				<Superficie>57.00</Superficie>
				<Transmitancia>0.99</Transmitancia>
				<ModoDeObtencion>Usuario</ModoDeObtencion>
				<Capas>
					<Capa>
						<Material>Azulejo cerámico</Material>
						<Espesor>0.0300</Espesor>
						<ConductividadTermica>1.30</ConductividadTermica>
						<Densidad>2300.00</Densidad>
						<FactorResistenciaVapor>0.20</FactorResistenciaVapor>
						<CalorEspecifico>840.00</CalorEspecifico>
					</Capa>
					<Capa>
						<Material>Mortero de cemento o cal para albañilería y para revoco/enlucido 1000 &lt; d &lt; 1250</Material>
						<Espesor>0.0100</Espesor>
						<ConductividadTermica>0.55</ConductividadTermica>
						<Densidad>1125.00</Densidad>
						<FactorResistenciaVapor>0.20</FactorResistenciaVapor>
						<CalorEspecifico>1000.00</CalorEspecifico>
					</Capa>
					<Capa>
						<Material>Hormigón en masa 2000 &lt; d &lt; 2300</Material>
						<Espesor>0.2100</Espesor>
						<ConductividadTermica>1.65</ConductividadTermica>
						<Densidad>2150.00</Densidad>
						<FactorResistenciaVapor>0.20</FactorResistenciaVapor>
						<CalorEspecifico>1000.00</CalorEspecifico>
					</Capa>
					<Capa>
						<Material>Tierra vegetal [d &lt; 2050]</Material>
						<Espesor>0.3500</Espesor>
						<ConductividadTermica>0.52</ConductividadTermica>
						<Densidad>2050.00</Densidad>
						<FactorResistenciaVapor>0.20</FactorResistenciaVapor>
						<CalorEspecifico>1840.00</CalorEspecifico>
					</Capa>
				</Capas>
			</Elemento>
			<Elemento>
				<Nombre>Medianera</Nombre>
				<Tipo>CERRAMIENTOS CSS</Tipo>
				<Superficie>160.89</Superficie>
				<Transmitancia>1.01</Transmitancia>
				<ModoDeObtencion>Usuario</ModoDeObtencion>
				<Capas>
					<Capa>
						<Material>1/2 pie LM métrico o catalán 40 mm&lt; G &lt; 50 mm</Material>
						<Espesor>0.1150</Espesor>
						<ConductividadTermica>1.02</ConductividadTermica>
						<Densidad>2170.00</Densidad>
						<FactorResistenciaVapor>0.20</FactorResistenciaVapor>
						<CalorEspecifico>1000.00</CalorEspecifico>
					</Capa>
					<Capa>
						<Material>Mortero de cemento o cal para albañilería y para revoco/enlucido 1000 &lt; d &lt; 1250</Material>
						<Espesor>0.0100</Espesor>
						<ConductividadTermica>0.55</ConductividadTermica>
						<Densidad>1125.00</Densidad>
						<FactorResistenciaVapor>0.20</FactorResistenciaVapor>
						<CalorEspecifico>1000.00</CalorEspecifico>
					</Capa>
					<Capa>
						<Material>EPS Poliestireno Expandido [ 0.037 W/[mK]]</Material>
						<Espesor>0.0200</Espesor>
						<ConductividadTermica>0.04</ConductividadTermica>
						<Densidad>30.00</Densidad>
						<FactorResistenciaVapor>0.20</FactorResistenciaVapor>
						<CalorEspecifico>1000.00</CalorEspecifico>
					</Capa>
					<Capa>
						<Material>Tabicón de LH doble [60 mm &lt; E &lt; 90 mm]</Material>
						<Espesor>0.0600</Espesor>
						<ConductividadTermica>0.47</ConductividadTermica>
						<Densidad>930.00</Densidad>
						<FactorResistenciaVapor>0.20</FactorResistenciaVapor>
						<CalorEspecifico>1000.00</CalorEspecifico>
					</Capa>
					<Capa>
						<Material>Enlucido de yeso 1000 &lt; d &lt; 1300</Material>
						<Espesor>0.0100</Espesor>
						<ConductividadTermica>0.57</ConductividadTermica>
						<Densidad>1150.00</Densidad>
						<FactorResistenciaVapor>0.20</FactorResistenciaVapor>
						<CalorEspecifico>1000.00</CalorEspecifico>
					</Capa>
				</Capas>
			</Elemento>
		</CerramientosOpacos>
		<HuecosyLucernarios>
			<Elemento>
				<Nombre>VIDRIO SIMPLE CON ROTURA</Nombre>
				<Tipo>Hueco</Tipo>
				<Superficie>0.00</Superficie>
				<Transmitancia>5.44</Transmitancia>
				<FactorSolar>0.78</FactorSolar>
				<ModoDeObtencionTransmitancia>Usuario</ModoDeObtencionTransmitancia>
				<ModoDeObtencionFactorSolar>Usuario</ModoDeObtencionFactorSolar>
			</Elemento>
			<Elemento>
				<Nombre>VIDRIO DOBLE</Nombre>
				<Tipo>Hueco</Tipo>
				<Superficie>0.00</Superficie>
				<Transmitancia>2.20</Transmitancia>
				<FactorSolar>0.06</FactorSolar>
				<ModoDeObtencionTransmitancia>Usuario</ModoDeObtencionTransmitancia>
				<ModoDeObtencionFactorSolar>Usuario</ModoDeObtencionFactorSolar>
			</Elemento>
			<Elemento>
				<Nombre>VIDRIO BAJO EMISIVO</Nombre>
				<Tipo>Hueco</Tipo>
				<Superficie>0.00</Superficie>
				<Transmitancia>1.84</Transmitancia>
				<FactorSolar>0.64</FactorSolar>
				<ModoDeObtencionTransmitancia>Usuario</ModoDeObtencionTransmitancia>
				<ModoDeObtencionFactorSolar>Usuario</ModoDeObtencionFactorSolar>
			</Elemento>
			<Elemento>
				<Nombre>Puerta madera</Nombre>
                <Tipo>Hueco</Tipo>
				<Superficie>0.00</Superficie>
				<Transmitancia>2.20</Transmitancia>
				<FactorSolar>0.04</FactorSolar>
				<ModoDeObtencionTransmitancia>Usuario</ModoDeObtencionTransmitancia>
				<ModoDeObtencionFactorSolar>Usuario</ModoDeObtencionFactorSolar>
			</Elemento>
		</HuecosyLucernarios>
	</DatosEnvolventeTermica>
    <InstalacionesTermicas>
	<GeneradoresDeCalefaccion>
		<Generador>
			<Nombre>EQ_Caldera-Electrica-Defecto</Nombre>
			<Tipo>Caldera eléctrica o de combustible</Tipo>
			<PotenciaNominal>10.00</PotenciaNominal>
			<RendimientoNominal>0.90</RendimientoNominal>
			<VectorEnergetico>Electricidad</VectorEnergetico>
			<VectorEnergetico>Usuario</VectorEnergetico>
		</Generador>
	</GeneradoresDeCalefaccion>
	<GeneradoresDeRefrigeracion>
		<Generador>
			<Nombre>EQ_Caldera-Electrica-Defecto</Nombre>
			<Tipo>Caldera eléctrica o de combustible</Tipo>
			<PotenciaNominal>10.00</PotenciaNominal>
			<RendimientoNominal>0.90</RendimientoNominal>
			<VectorEnergetico>Electricidad</VectorEnergetico>
			<VectorEnergetico>Usuario</VectorEnergetico>
		</Generador>
	</GeneradoresDeRefrigeracion>
	<InstalacionesACS>
		<Instalacion>
			<Nombre>EQ_Caldera-Electrica-Defecto</Nombre>
			<Tipo>Caldera eléctrica o de combustible</Tipo>
			<PotenciaNominal>10.00</PotenciaNominal>
			<RendimientoNominal>0.90</RendimientoNominal>
			<VectorEnergetico>Electricidad</VectorEnergetico>
			<VectorEnergetico>Usuario</VectorEnergetico>
		</Instalacion>
	</InstalacionesACS>
    </InstalacionesTermicas>
	<InstalacionesIluminacion>
		<Espacio>
			<Nombre>P01_E01</Nombre>
			<PotenciaInstalada>4.40</PotenciaInstalada>
			<VEEI>7.00</VEEI>
			<IluminanciaMedia>7.00</IluminanciaMedia>
			<ModoDeObtencion>Usuario</ModoDeObtencion>
		</Espacio>
		<PotenciaTotalInstalada>4.40</PotenciaTotalInstalada>
		<Espacio>
			<Nombre>P02_E01</Nombre>
			<PotenciaInstalada>4.40</PotenciaInstalada>
			<VEEI>7.00</VEEI>
			<IluminanciaMedia>7.00</IluminanciaMedia>
			<ModoDeObtencion>Usuario</ModoDeObtencion>
		</Espacio>
		<Espacio>
			<Nombre>P02_E02</Nombre>
			<PotenciaInstalada>4.40</PotenciaInstalada>
			<VEEI>7.00</VEEI>
			<IluminanciaMedia>7.00</IluminanciaMedia>
			<ModoDeObtencion>Usuario</ModoDeObtencion>
		</Espacio>
		<Espacio>
			<Nombre>P02_E03</Nombre>
			<PotenciaInstalada>4.40</PotenciaInstalada>
			<VEEI>7.00</VEEI>
			<IluminanciaMedia>7.00</IluminanciaMedia>
			<ModoDeObtencion>Usuario</ModoDeObtencion>
		</Espacio>
		<Espacio>
			<Nombre>P02_E04</Nombre>
			<PotenciaInstalada>4.40</PotenciaInstalada>
			<VEEI>7.00</VEEI>
			<IluminanciaMedia>7.00</IluminanciaMedia>
			<ModoDeObtencion>Usuario</ModoDeObtencion>
		</Espacio>
		<PotenciaTotalInstalada>22.00</PotenciaTotalInstalada>
		<Espacio>
			<Nombre>P03_E01</Nombre>
			<PotenciaInstalada>4.40</PotenciaInstalada>
			<VEEI>7.00</VEEI>
			<IluminanciaMedia>7.00</IluminanciaMedia>
			<ModoDeObtencion>Usuario</ModoDeObtencion>
		</Espacio>
		<Espacio>
			<Nombre>P03_E02</Nombre>
			<PotenciaInstalada>4.40</PotenciaInstalada>
			<VEEI>7.00</VEEI>
			<IluminanciaMedia>7.00</IluminanciaMedia>
			<ModoDeObtencion>Usuario</ModoDeObtencion>
		</Espacio>
		<Espacio>
			<Nombre>P03_E03</Nombre>
			<PotenciaInstalada>4.40</PotenciaInstalada>
			<VEEI>7.00</VEEI>
			<IluminanciaMedia>7.00</IluminanciaMedia>
			<ModoDeObtencion>Usuario</ModoDeObtencion>
		</Espacio>
		<Espacio>
			<Nombre>P03_E04</Nombre>
			<PotenciaInstalada>4.40</PotenciaInstalada>
			<VEEI>7.00</VEEI>
			<IluminanciaMedia>7.00</IluminanciaMedia>
			<ModoDeObtencion>Usuario</ModoDeObtencion>
		</Espacio>
		<Espacio>
			<Nombre>P03_E05</Nombre>
			<PotenciaInstalada>4.40</PotenciaInstalada>
			<VEEI>7.00</VEEI>
			<IluminanciaMedia>7.00</IluminanciaMedia>
			<ModoDeObtencion>Usuario</ModoDeObtencion>
		</Espacio>
		<Espacio>
			<Nombre>P03_E06</Nombre>
			<PotenciaInstalada>4.40</PotenciaInstalada>
			<VEEI>7.00</VEEI>
			<IluminanciaMedia>7.00</IluminanciaMedia>
			<ModoDeObtencion>Usuario</ModoDeObtencion>
		</Espacio>
		<PotenciaTotalInstalada>48.40</PotenciaTotalInstalada>
		<Espacio>
			<Nombre>P04_E01</Nombre>
			<PotenciaInstalada>4.40</PotenciaInstalada>
			<VEEI>7.00</VEEI>
			<IluminanciaMedia>7.00</IluminanciaMedia>
			<ModoDeObtencion>Usuario</ModoDeObtencion>
		</Espacio>
		<PotenciaTotalInstalada>52.80</PotenciaTotalInstalada>
	</InstalacionesIluminacion>
	<CondicionesFuncionamientoyOcupacion>
		<Espacio>
			<Espacio>P01_E01</Espacio>
			<Superficie>57.00</Superficie>
			<NivelDeAcondicionamiento>Acondicionado</NivelDeAcondicionamiento>
			<PerfilDeUso>residencial-24h-baja</PerfilDeUso>
		</Espacio>
		<Espacio>
			<Espacio>P02_E01</Espacio>
			<Superficie>3.55</Superficie>
			<NivelDeAcondicionamiento>Acondicionado</NivelDeAcondicionamiento>
			<PerfilDeUso>residencial-24h-baja</PerfilDeUso>
		</Espacio>
		<Espacio>
			<Espacio>P02_E02</Espacio>
			<Superficie>9.77</Superficie>
			<NivelDeAcondicionamiento>Acondicionado</NivelDeAcondicionamiento>
			<PerfilDeUso>residencial-24h-baja</PerfilDeUso>
		</Espacio>
		<Espacio>
			<Espacio>P02_E03</Espacio>
			<Superficie>13.27</Superficie>
			<NivelDeAcondicionamiento>Acondicionado</NivelDeAcondicionamiento>
			<PerfilDeUso>residencial-24h-baja</PerfilDeUso>
		</Espacio>
		<Espacio>
			<Espacio>P02_E04</Espacio>
			<Superficie>23.85</Superficie>
			<NivelDeAcondicionamiento>Acondicionado</NivelDeAcondicionamiento>
			<PerfilDeUso>residencial-24h-baja</PerfilDeUso>
		</Espacio>
		<Espacio>
			<Espacio>P03_E01</Espacio>
			<Superficie>8.59</Superficie>
			<NivelDeAcondicionamiento>Acondicionado</NivelDeAcondicionamiento>
			<PerfilDeUso>residencial-24h-baja</PerfilDeUso>
		</Espacio>
		<Espacio>
			<Espacio>P03_E02</Espacio>
			<Superficie>12.28</Superficie>
			<NivelDeAcondicionamiento>Acondicionado</NivelDeAcondicionamiento>
			<PerfilDeUso>residencial-24h-baja</PerfilDeUso>
		</Espacio>
		<Espacio>
			<Espacio>P03_E03</Espacio>
			<Superficie>8.23</Superficie>
			<NivelDeAcondicionamiento>Acondicionado</NivelDeAcondicionamiento>
			<PerfilDeUso>residencial-24h-baja</PerfilDeUso>
		</Espacio>
		<Espacio>
			<Espacio>P03_E04</Espacio>
			<Superficie>14.59</Superficie>
			<NivelDeAcondicionamiento>Acondicionado</NivelDeAcondicionamiento>
			<PerfilDeUso>residencial-24h-baja</PerfilDeUso>
		</Espacio>
		<Espacio>
			<Espacio>P03_E05</Espacio>
			<Superficie>5.69</Superficie>
			<NivelDeAcondicionamiento>Acondicionado</NivelDeAcondicionamiento>
			<PerfilDeUso>residencial-24h-baja</PerfilDeUso>
		</Espacio>
		<Espacio>
			<Espacio>P03_E06</Espacio>
			<Superficie>7.61</Superficie>
			<NivelDeAcondicionamiento>Acondicionado</NivelDeAcondicionamiento>
			<PerfilDeUso>residencial-24h-baja</PerfilDeUso>
		</Espacio>
		<Espacio>
			<Espacio>P04_E01</Espacio>
			<Superficie>57.00</Superficie>
			<NivelDeAcondicionamiento>NoHabitable</NivelDeAcondicionamiento>
			<PerfilDeUso>nohabitable</PerfilDeUso>
		</Espacio>
	</CondicionesFuncionamientoyOcupacion>
	<EmisionesCO2>
		<Global>8.47</Global>
		<Calefaccion>2.71</Calefaccion>
		<Refrigeracion>4.19</Refrigeracion>
		<ACS>1.58</ACS>
		<Iluminacion>8.03</Iluminacion>
	</EmisionesCO2>
	<Calificacion>
		<EmisionesCO2>
			<Global>B</Global>
			<Calefaccion>A</Calefaccion>
			<Refrigeracion>B</Refrigeracion>
			<ACS>B</ACS>
			<Iluminacion>-</Iluminacion>
		</EmisionesCO2>
		<Demanda>
			<Calefaccion>A</Calefaccion>
			<Refrigeracion>A</Refrigeracion>
		</Demanda>
		<EnergiaPrimariaNoRenovable>
			<Global>B</Global>
			<Calefaccion>A</Calefaccion>
			<Refrigeracion>B</Refrigeracion>
			<ACS>B</ACS>
			<Iluminacion>-</Iluminacion>
		</EnergiaPrimariaNoRenovable>
	</Calificacion>
	<Demanda>
		<EdificioObjeto>
			<Global/>
			<Calefaccion>12.13</Calefaccion>
			<Refrigeracion>12.82</Refrigeracion>
			<ACS/>
			<Conjunta/>
			<Calefaccion08/>
			<Refrigeracion08/>
			<Conjunta08/>
			<Ahorro08/>
		</EdificioObjeto>
		<EdificioReferencia>
			<Global/>
			<Calefaccion>0.00</Calefaccion>
			<Refrigeracion>0.00</Refrigeracion>
			<ACS/>
			<Conjunta/>
			<Calefaccion08/>
			<Refrigeracion08/>
			<Conjunta08/>
			<Ahorro08/>
		</EdificioReferencia>
		<Exigencias>
			<LimiteCalefaccionVivienda>15.00</LimiteCalefaccionVivienda>
			<LimiteRefrigeracionVivienda>20.00</LimiteRefrigeracionVivienda>
			<LimiteAhorroOtrosUsos/>
		</Exigencias>
	</Demanda>
	<Consumo>
		<FactoresdePaso>
			<FinalAPrimariaNoRenovable>
				<GasNatural>1.011</GasNatural>
				<GasoleoC>1.081</GasoleoC>
				<GLP>1.081</GLP>
				<Carbon>1.000</Carbon>
				<BiomasaPellet>0.085</BiomasaPellet>
				<BiomasaOtros>0.034</BiomasaOtros>
				<ElectricidadPeninsular>2.603</ElectricidadPeninsular>
				<ElectricidadBaleares>3.347</ElectricidadBaleares>
				<ElectricidadCanarias>3.347</ElectricidadCanarias>
				<ElectricidadCeutayMelilla>3.347</ElectricidadCeutayMelilla>
			</FinalAPrimariaNoRenovable>
			<FinalAEmisiones>
				<GasNatural>0.204</GasNatural>
				<GasoleoC>0.287</GasoleoC>
				<GLP>0,244</GLP>
				<Carbon>0.347</Carbon>
				<BiomasaPellet>0.000</BiomasaPellet>
				<BiomasaOtros>0.000</BiomasaOtros>
				<ElectricidadPeninsular>0.649</ElectricidadPeninsular>
				<ElectricidadBaleares>0.981</ElectricidadBaleares>
				<ElectricidadCanarias>0.981</ElectricidadCanarias>
				<ElectricidadCeutayMelilla>0.981</ElectricidadCeutayMelilla>
			</FinalAEmisiones>
		</FactoresdePaso>
		<EnergiaFinalVectores>
			<Global>36.54</Global>
			<Calefaccion>-12.13</Calefaccion>
			<Refrigeracion>12.82</Refrigeracion>
			<ACS/>
			<Iluminacion/>
		</EnergiaFinalVectores>
		<EnergiaPrimariaNoRenovable>
			<Global>36.54</Global>
			<Calefaccion>13.28</Calefaccion>
			<Refrigeracion>6.45</Refrigeracion>
			<ACS>2.43</ACS>
			<Iluminacion>0.00</Iluminacion>
		</EnergiaPrimariaNoRenovable>
		<Exigencias>
			<LimiteViviendaGlobalEPNR>51.081413269043</LimiteViviendaGlobalEPNR>
			<LimiteTerciarioGlobalEPR/>
			<Calificacion/>
		</Exigencias>
	</Consumo>
	<PruebasComprobacionesInspecciones/>
	<DatosPersonalizados/>
</DatosEnergeticosDelEdificio>
